{
    "ID": "207",
    "PlaceName": "Thornmarch",
    "Code": "f1fa",
    "Map": {
        "ID": "36",
        "FixedTime": "-1",
        "SizeFactor": "400",
        "Offset X": "0",
        "Offset Y": "0",
        "EventMap": "False",
        "CanMount": "False",
        "CanStealth": "False",
        "SearchPlayer": "True",
        "Weather": [
            "Gloom"
        ],
        "ArrayHandler": [],
        "MapMarker": [
            {
                "Key": "0.0",
                "Icon": "000000",
                "coords": [
                    0,
                    0
                ],
                "SubText": "",
                "SubtextOrientation": "left",
                "Type": "0",
                "Data": ""
            }
        ]
    },
    "BGPath": "ffxiv\/fst_f1\/fld\/f1fa\/level\/f1fa",
    "BGM": {
        "ID": "1001",
        "BGM": {
            "Day": "music\/ffxiv\/BGM_Null.scd",
            "Night": "music\/ffxiv\/BGM_Null.scd",
            "Battle": "music\/ffxiv\/BGM_Null.scd",
            "Dawn": ""
        }
    },
    "ExclusiveType": "2",
    "LGB_Data": {
        "Vfx": [],
        "PositionMarker": [],
        "Gimmick": [
            {
                "LGB_ID": 4377976,
                "AssetType": 6,
                "Name": "LVD_zone_01",
                "AssetPath": "bgcommon\/world\/lvd\/shared\/for_vfx\/sgvf_w_lvd_b0095.sgb",
                "DoorState": 1,
                "Transform": {
                    "X": 0.01409468,
                    "Y": 14.89947,
                    "Coords": {
                        "X": 6.125282168886719,
                        "Y": 6.423280405273438
                    },
                    "Pixel": {
                        "X": 1025.0564337773437,
                        "Y": 1084.6560810546875
                    }
                }
            }
        ],
        "Sound": [],
        "EventNPC": [],
        "Aetheryte": [],
        "EnvSpace": [],
        "PopRange": [],
        "exitrange": [],
        "MapRange": [],
        "EventObject": [
            {
                "LGB_ID": 4377979,
                "AssetType": 45,
                "Name": "LVD_zone_01",
                "EobjId": "2000182",
                "EobjName": "",
                "EobjData": {
                    "ExportedSG": null
                },
                "Transform": {
                    "X": -5.269677,
                    "Y": 14.25764,
                    "Coords": {
                        "X": 6.019503536621094,
                        "Y": 6.41043126953125
                    },
                    "Pixel": {
                        "X": 1003.9007073242187,
                        "Y": 1082.08625390625
                    }
                }
            },
            {
                "LGB_ID": 4377980,
                "AssetType": 45,
                "Name": "LVD_zone_01",
                "EobjId": "2000139",
                "EobjName": "Exit",
                "EobjData": {
                    "VFX": "bgcommon\/world\/lvd\/shared\/for_vfx\/sgvf_w_lvd_b0005.sgb"
                },
                "Transform": {
                    "X": 0.01429753,
                    "Y": -17.78625,
                    "Coords": {
                        "X": 6.1252862298486335,
                        "Y": 5.7689276123046875
                    },
                    "Pixel": {
                        "X": 1025.0572459697266,
                        "Y": 953.7855224609375
                    }
                }
            }
        ],
        "EnvLocation": [],
        "Fate": [],
        "EventRange": [],
        "CollisionBox": [],
        "LineVfx": [],
        "ClientPath": [],
        "TargetMarker": [],
        "ChairMarker": [],
        "PrefetchRange": [],
        "Treasure": [],
        "BNPC": [],
        "Gathering": []
    }
}