{
    "ID": "428",
    "PlaceName": "Seat of the Lord Commander",
    "Code": "r2e3",
    "Map": {
        "ID": "221",
        "FixedTime": "-1",
        "SizeFactor": "400",
        "Offset X": "0",
        "Offset Y": "0",
        "EventMap": "True",
        "CanMount": "False",
        "CanStealth": "False",
        "SearchPlayer": "True",
        "Weather": [
            "Fair Skies"
        ],
        "ArrayHandler": [
            "67139",
            "67169",
            "67177"
        ],
        "MapMarker": [
            {
                "Key": "0.0",
                "Icon": "000000",
                "coords": [
                    0,
                    0
                ],
                "SubText": "",
                "SubtextOrientation": "left",
                "Type": "0",
                "Data": ""
            }
        ]
    },
    "BGPath": "ex1\/01_roc_r2\/evt\/r2e3\/level\/r2e3",
    "BGM": {
        "ID": "1166",
        "BGM": {
            "Day": "music\/ex1\/BGM_EX1_Event_IshDragonHead.scd",
            "Night": "music\/ex1\/BGM_EX1_Event_IshDragonHead.scd",
            "Battle": "music\/ex1\/BGM_EX1_Battle_IshSebu_01.scd",
            "Dawn": ""
        }
    },
    "ExclusiveType": "0",
    "LGB_Data": {
        "Vfx": [],
        "PositionMarker": [],
        "Gimmick": [],
        "Sound": [],
        "EventNPC": [
            {
                "LGB_ID": 5862692,
                "AssetType": 8,
                "Name": "QST_HeaVna302",
                "EnpcBase": "1012761",
                "EnpcName": "Aymeric",
                "Transform": {
                    "X": -0.0102255,
                    "Y": -6.112364,
                    "Coords": {
                        "X": 6.1247952902832035,
                        "Y": 6.002633337890625
                    },
                    "Pixel": {
                        "X": 1024.9590580566407,
                        "Y": 1000.5266675781251
                    }
                }
            },
            {
                "LGB_ID": 5908343,
                "AssetType": 8,
                "Name": "QST_HeaVna302",
                "EnpcBase": "1014316",
                "EnpcName": "Lucia",
                "Transform": {
                    "X": 1.327618,
                    "Y": -7.649118,
                    "Coords": {
                        "X": 6.151578290039062,
                        "Y": 5.971868243164063
                    },
                    "Pixel": {
                        "X": 1030.3156580078123,
                        "Y": 994.3736486328125
                    }
                }
            },
            {
                "LGB_ID": 5893557,
                "AssetType": 8,
                "Name": "QST_HeaVna405",
                "EnpcBase": "1013229",
                "EnpcName": "Estinien",
                "Transform": {
                    "X": -1.891607,
                    "Y": -3.657399,
                    "Coords": {
                        "X": 6.087130914550781,
                        "Y": 6.051780586425782
                    },
                    "Pixel": {
                        "X": 1017.4261829101562,
                        "Y": 1010.3561172851563
                    }
                }
            },
            {
                "LGB_ID": 5910715,
                "AssetType": 8,
                "Name": "QST_HeaVna405",
                "EnpcBase": "1014527",
                "EnpcName": "Alphinaud",
                "Transform": {
                    "X": 0.5896825,
                    "Y": -3.461664,
                    "Coords": {
                        "X": 6.136805167236328,
                        "Y": 6.0556991093749994
                    },
                    "Pixel": {
                        "X": 1027.3610334472655,
                        "Y": 1011.1398218749999
                    }
                }
            },
            {
                "LGB_ID": 5861239,
                "AssetType": 8,
                "Name": "QST_HeaVna601",
                "EnpcBase": "1013181",
                "EnpcName": "Alphinaud",
                "Transform": {
                    "X": -1.244144,
                    "Y": -2.471279,
                    "Coords": {
                        "X": 6.1000928203125,
                        "Y": 6.0755261528320315
                    },
                    "Pixel": {
                        "X": 1020.0185640625,
                        "Y": 1015.1052305664062
                    }
                }
            },
            {
                "LGB_ID": 5861240,
                "AssetType": 8,
                "Name": "QST_HeaVna601",
                "EnpcBase": "1013182",
                "EnpcName": "Cid",
                "Transform": {
                    "X": 1.038965,
                    "Y": -2.627922,
                    "Coords": {
                        "X": 6.145799592285156,
                        "Y": 6.072390233398437
                    },
                    "Pixel": {
                        "X": 1029.1599184570312,
                        "Y": 1014.4780466796874
                    }
                }
            },
            {
                "LGB_ID": 5861241,
                "AssetType": 8,
                "Name": "QST_HeaVna601",
                "EnpcBase": "1013183",
                "EnpcName": "Aymeric",
                "Transform": {
                    "X": 0.0009602159,
                    "Y": -6.289669,
                    "Coords": {
                        "X": 6.125019223072218,
                        "Y": 5.999083774902344
                    },
                    "Pixel": {
                        "X": 1025.0038446144436,
                        "Y": 999.8167549804688
                    }
                }
            },
            {
                "LGB_ID": 5861242,
                "AssetType": 8,
                "Name": "QST_HeaVna601",
                "EnpcBase": "1013184",
                "EnpcName": "Lucia",
                "Transform": {
                    "X": 2.668934,
                    "Y": -4.936186,
                    "Coords": {
                        "X": 6.178430807617187,
                        "Y": 6.026179870117188
                    },
                    "Pixel": {
                        "X": 1035.6861615234375,
                        "Y": 1005.2359740234376
                    }
                }
            },
            {
                "LGB_ID": 5861243,
                "AssetType": 8,
                "Name": "QST_HeaVna601",
                "EnpcBase": "1013185",
                "EnpcName": "Count Edmont de Fortemps",
                "Transform": {
                    "X": -2.346727,
                    "Y": -4.287831,
                    "Coords": {
                        "X": 6.078019625488282,
                        "Y": 6.039159633300781
                    },
                    "Pixel": {
                        "X": 1015.6039250976564,
                        "Y": 1007.8319266601562
                    }
                }
            },
            {
                "LGB_ID": 6212174,
                "AssetType": 8,
                "Name": "QST_HeaVnc108",
                "EnpcBase": "1016024",
                "EnpcName": "Count Edmont de Fortemps",
                "Transform": {
                    "X": -0.9847968,
                    "Y": -4.053026,
                    "Coords": {
                        "X": 6.1052848296875,
                        "Y": 6.043860319335938
                    },
                    "Pixel": {
                        "X": 1021.0569659375001,
                        "Y": 1008.7720638671875
                    }
                }
            },
            {
                "LGB_ID": "5861239",
                "AssetType": "8",
                "Name": "",
                "AssetObject": "1013181",
                "EventID": "0",
                "EnpcBase": "1013181",
                "EnpcName": "Alphinaud",
                "Transform": {
                    "X": "-1.24414",
                    "Y": "-2.47128",
                    "Coords": {
                        "X": 6.100092900390625,
                        "Y": 6.0755261328125
                    },
                    "Pixel": {
                        "X": 1020.0185800781251,
                        "Y": 1015.1052265625
                    }
                }
            },
            {
                "LGB_ID": "5861240",
                "AssetType": "8",
                "Name": "",
                "AssetObject": "1013182",
                "EventID": "0",
                "EnpcBase": "1013182",
                "EnpcName": "Cid",
                "Transform": {
                    "X": "1.03896",
                    "Y": "-2.62792",
                    "Coords": {
                        "X": 6.1457994921875,
                        "Y": 6.072390273437501
                    },
                    "Pixel": {
                        "X": 1029.1598984375,
                        "Y": 1014.4780546875002
                    }
                }
            },
            {
                "LGB_ID": "5861241",
                "AssetType": "8",
                "Name": "",
                "AssetObject": "1013183",
                "EventID": "0",
                "EnpcBase": "1013183",
                "EnpcName": "Aymeric",
                "Transform": {
                    "X": "0",
                    "Y": "-6.28967",
                    "Coords": {
                        "X": 6.125,
                        "Y": 5.999083754882813
                    },
                    "Pixel": {
                        "X": 1025,
                        "Y": 999.8167509765626
                    }
                }
            },
            {
                "LGB_ID": "5861242",
                "AssetType": "8",
                "Name": "",
                "AssetObject": "1013184",
                "EventID": "0",
                "EnpcBase": "1013184",
                "EnpcName": "Lucia",
                "Transform": {
                    "X": "2.66893",
                    "Y": "-4.93619",
                    "Coords": {
                        "X": 6.178430727539062,
                        "Y": 6.026179790039063
                    },
                    "Pixel": {
                        "X": 1035.6861455078124,
                        "Y": 1005.2359580078125
                    }
                }
            },
            {
                "LGB_ID": "5861243",
                "AssetType": "8",
                "Name": "",
                "AssetObject": "1013185",
                "EventID": "0",
                "EnpcBase": "1013185",
                "EnpcName": "Count Edmont de Fortemps",
                "Transform": {
                    "X": "-2.34673",
                    "Y": "-4.28783",
                    "Coords": {
                        "X": 6.078019565429687,
                        "Y": 6.039159653320313
                    },
                    "Pixel": {
                        "X": 1015.6039130859375,
                        "Y": 1007.8319306640626
                    }
                }
            },
            {
                "LGB_ID": "5862692",
                "AssetType": "8",
                "Name": "",
                "AssetObject": "1012761",
                "EventID": "0",
                "EnpcBase": "1012761",
                "EnpcName": "Aymeric",
                "Transform": {
                    "X": "-0.0102255",
                    "Y": "-6.11236",
                    "Coords": {
                        "X": 6.1247952902832035,
                        "Y": 6.00263341796875
                    },
                    "Pixel": {
                        "X": 1024.9590580566407,
                        "Y": 1000.5266835937499
                    }
                }
            },
            {
                "LGB_ID": "5893557",
                "AssetType": "8",
                "Name": "",
                "AssetObject": "1013229",
                "EventID": "0",
                "EnpcBase": "1013229",
                "EnpcName": "Estinien",
                "Transform": {
                    "X": "-1.89161",
                    "Y": "-3.6574",
                    "Coords": {
                        "X": 6.087130854492187,
                        "Y": 6.05178056640625
                    },
                    "Pixel": {
                        "X": 1017.4261708984375,
                        "Y": 1010.3561132812499
                    }
                }
            },
            {
                "LGB_ID": "5908343",
                "AssetType": "8",
                "Name": "",
                "AssetObject": "1014316",
                "EventID": "0",
                "EnpcBase": "1014316",
                "EnpcName": "Lucia",
                "Transform": {
                    "X": "1.32762",
                    "Y": "-7.64912",
                    "Coords": {
                        "X": 6.1515783300781255,
                        "Y": 5.971868203125
                    },
                    "Pixel": {
                        "X": 1030.315666015625,
                        "Y": 994.373640625
                    }
                }
            },
            {
                "LGB_ID": "6212174",
                "AssetType": "8",
                "Name": "",
                "AssetObject": "1016024",
                "EventID": "0",
                "EnpcBase": "1016024",
                "EnpcName": "Count Edmont de Fortemps",
                "Transform": {
                    "X": "-0.984797",
                    "Y": "-4.05303",
                    "Coords": {
                        "X": 6.105284825683594,
                        "Y": 6.043860239257812
                    },
                    "Pixel": {
                        "X": 1021.0569651367188,
                        "Y": 1008.7720478515624
                    }
                }
            }
        ],
        "Aetheryte": [],
        "EnvSpace": [],
        "PopRange": [
            {
                "LGB_ID": 5861351,
                "AssetType": 40,
                "Name": "QST_HeaVna601",
                "relativePosCount": 20,
                "Transform": {
                    "X": 0,
                    "Y": 7.5,
                    "Scale": 0.5,
                    "Coords": {
                        "X": 6.125,
                        "Y": 6.275146484375
                    },
                    "Pixel": {
                        "X": 1025,
                        "Y": 1055.029296875
                    }
                }
            },
            {
                "LGB_ID": 5821838,
                "AssetType": 40,
                "Name": "QST_WARP_01",
                "relativePosCount": 20,
                "Transform": {
                    "X": -0.006786406,
                    "Y": 7.577866,
                    "Scale": 0.75,
                    "Coords": {
                        "X": 6.124864139333008,
                        "Y": 6.276705325195312
                    },
                    "Pixel": {
                        "X": 1024.9728278666016,
                        "Y": 1055.3410650390624
                    }
                }
            },
            {
                "LGB_ID": "5821838",
                "AssetType": "40",
                "Name": "",
                "AssetObject": "0",
                "EventID": "0",
                "Transform": {
                    "X": "-0.00678641",
                    "Y": "7.57787",
                    "Scale": 0.1875,
                    "Coords": {
                        "X": 6.12486413925293,
                        "Y": 6.276705405273438
                    },
                    "Pixel": {
                        "X": 1024.9728278505859,
                        "Y": 1055.3410810546875
                    }
                }
            },
            {
                "LGB_ID": "5861351",
                "AssetType": "40",
                "Name": "",
                "AssetObject": "0",
                "EventID": "0",
                "Transform": {
                    "X": "0",
                    "Y": "7.5",
                    "Scale": 0.125,
                    "Coords": {
                        "X": 6.125,
                        "Y": 6.275146484375
                    },
                    "Pixel": {
                        "X": 1025,
                        "Y": 1055.029296875
                    }
                }
            }
        ],
        "exitrange": [],
        "MapRange": [],
        "EventObject": [
            {
                "LGB_ID": 5821831,
                "AssetType": 45,
                "Name": "QST_WARP_01",
                "EobjId": "2005333",
                "EobjName": "Exit",
                "EobjData": {
                    "WarpID": "131194",
                    "WarpName": "",
                    "WarpQuestion": "Leave the Seat of the Lord Commander?"
                },
                "Transform": {
                    "X": -0.00864544,
                    "Y": 9.627425,
                    "Coords": {
                        "X": 6.1248269223437495,
                        "Y": 6.317736535644531
                    },
                    "Pixel": {
                        "X": 1024.9653844687498,
                        "Y": 1063.5473071289064
                    }
                }
            }
        ],
        "EnvLocation": [],
        "Fate": [],
        "EventRange": [],
        "CollisionBox": [],
        "LineVfx": [],
        "ClientPath": [],
        "TargetMarker": [],
        "ChairMarker": [],
        "PrefetchRange": [],
        "Treasure": [],
        "BNPC": [],
        "Gathering": []
    }
}